MANIFEST.in
README.md
setup.py
tomograph/__init__.py
tomograph/__main__.py
tomograph/cli.py
tomograph/model.py
tomograph/transform.py
tomograph/utils.py
tomograph.egg-info/PKG-INFO
tomograph.egg-info/SOURCES.txt
tomograph.egg-info/dependency_links.txt
tomograph.egg-info/entry_points.txt
tomograph.egg-info/requires.txt
tomograph.egg-info/top_level.txt